html2epub/__init__.py
html2epub/chapter.py
html2epub/clean.py
html2epub/constants.py
html2epub/epub.py
html2epub/epub_templates/container.xml
html2epub/epub_templates/mimetype
html2epub/epub_templates/opf.xml
html2epub/epub_templates/toc.html
html2epub/epub_templates/toc_ncx.xml
html2epub-1.3.dist-info/licenses/License.txt
html2epub-1.3.dist-info/METADATA
html2epub-1.3.dist-info/WHEEL
html2epub-1.3.dist-info/top_level.txt
html2epub-1.3.dist-info/RECORD
