Metadata-Version: 2.4
Name: html2epub
Version: 1.3
Summary: 将 html链接, html文件 或 html文本 转换成 epub文件.
Home-page: https://github.com/zzZ5/Html2Epub
Author: zzZ5
Author-email: baoju_liu@foxmail.com
Classifier: Programming Language :: Python :: 3
Classifier: Programming Language :: Python :: 3.8
Classifier: Programming Language :: Python :: 3.9
Classifier: Programming Language :: Python :: 3.10
Classifier: Programming Language :: Python :: 3.11
Classifier: Programming Language :: Python :: 3.12
Classifier: Programming Language :: Python :: 3.13
Classifier: License :: OSI Approved :: MIT License
Classifier: Operating System :: OS Independent
License-File: License.txt
Requires-Dist: beautifulsoup4>=4.7.1
Requires-Dist: jinja2>=2.10.1
Requires-Dist: lxml>=4.3.4
Requires-Dist: requests>=2.22.0
Dynamic: author
Dynamic: author-email
Dynamic: classifier
Dynamic: description
Dynamic: description-content-type
Dynamic: home-page
Dynamic: license-file
Dynamic: requires-dist
Dynamic: summary
